logger/__init__.py
logger/logger.py
neomate/NeoMate.py
neomate/__init__.py
neomate/base.py
neomate/orm.py
utils/__init__.py
utils/utils.py
neomate-0.1.1.dist-info/METADATA
neomate-0.1.1.dist-info/WHEEL
neomate-0.1.1.dist-info/top_level.txt
neomate-0.1.1.dist-info/RECORD
