Metadata-Version: 2.2
Name: neomate
Version: 0.1.1
Summary: Lightweight Neo4j ORM with type validation and relationship management
Home-page: https://github.com/yourusername/neomate
Author: MrRac
Author-email: trew5804@gmail.com
Project-URL: Bug Tracker, https://github.com/cashelastest/neomate/issues
Project-URL: Documentation, https://github.com/cashelastest/neomate#readme
Project-URL: Source Code, https://github.com/cashelastest/neomate
Keywords: orm,database,graph database,type validation,relationship management
Classifier: Development Status :: 3 - Alpha
Classifier: Intended Audience :: Developers
Classifier: Topic :: Database :: Database Engines/Servers
Classifier: Topic :: Software Development :: Libraries :: Python Modules
Classifier: Topic :: Database
Classifier: Programming Language :: Python :: 3
Classifier: Programming Language :: Python :: 3.7
Classifier: Programming Language :: Python :: 3.8
Classifier: Programming Language :: Python :: 3.9
Classifier: Programming Language :: Python :: 3.10
Classifier: Programming Language :: Python :: 3.11
Classifier: License :: OSI Approved :: MIT License
Classifier: Operating System :: OS Independent
Requires-Python: >=3.7
Requires-Dist: neo4j-driver>=4.4.0
Requires-Dist: colorlog>=6.7.0
Requires-Dist: dataclasses; python_version < "3.7"
Provides-Extra: dev
Requires-Dist: pytest>=7.0.0; extra == "dev"
Requires-Dist: pytest-mock>=3.10.0; extra == "dev"
Requires-Dist: black; extra == "dev"
Requires-Dist: flake8; extra == "dev"
Dynamic: author
Dynamic: author-email
Dynamic: classifier
Dynamic: description
Dynamic: description-content-type
Dynamic: home-page
Dynamic: keywords
Dynamic: project-url
Dynamic: provides-extra
Dynamic: requires-dist
Dynamic: requires-python
Dynamic: summary
